masbench/cli.py
masbench-0.1.0.dist-info/licenses/LICENSE
masbench-0.1.0.dist-info/METADATA
masbench-0.1.0.dist-info/WHEEL
masbench-0.1.0.dist-info/entry_points.txt
masbench-0.1.0.dist-info/top_level.txt
masbench-0.1.0.dist-info/RECORD
